worldengine/__init__.py
worldengine/__main__.py
worldengine/astar.py
worldengine/basic_map_operations.py
worldengine/biome.py
worldengine/common.py
worldengine/draw.py
worldengine/drawing_functions.py
worldengine/generation.py
worldengine/hdf5_serialization.py
worldengine/image_io.py
worldengine/plates.py
worldengine/step.py
worldengine/version.py
worldengine/world.py
worldengine/cli/__init__.py
worldengine/cli/main.py
worldengine/imex/__init__.py
worldengine/protobuf/World_pb2.py
worldengine/protobuf/__init__.py
worldengine/simulations/__init__.py
worldengine/simulations/basic.py
worldengine/simulations/biome.py
worldengine/simulations/erosion.py
worldengine/simulations/humidity.py
worldengine/simulations/hydrology.py
worldengine/simulations/icecap.py
worldengine/simulations/irrigation.py
worldengine/simulations/permeability.py
worldengine/simulations/precipitation.py
worldengine/simulations/temperature.py
worldengine-0.19.0.dist-info/DESCRIPTION.rst
worldengine-0.19.0.dist-info/METADATA
worldengine-0.19.0.dist-info/RECORD
worldengine-0.19.0.dist-info/WHEEL
worldengine-0.19.0.dist-info/entry_points.txt
worldengine-0.19.0.dist-info/metadata.json
worldengine-0.19.0.dist-info/top_level.txt
