Metadata-Version: 1.1
Name: worldengine
Version: 0.19.0
Summary: World generator simulating plate tectonics, erosion, etc.
Home-page: http://github.com/Mindwerks/worldengine
Author: Federico Tomassetti, Bret Curtis
Author-email: f.tomassetti@gmail.com, psi29a@gmail.com
License: MIT License
Download-URL: https://github.com/Mindwerks/worldengine/releases
Platform: UNKNOWN
